picodb.py
PicoDB-0.1.1.dist-info/METADATA
PicoDB-0.1.1.dist-info/WHEEL
PicoDB-0.1.1.dist-info/top_level.txt
PicoDB-0.1.1.dist-info/RECORD
